Metadata-Version: 1.0
Name: vonMises
Version: 1.0.1
Summary: Package for vonMises distribution
Home-page: UNKNOWN
Author: UNKNOWN
Author-email: UNKNOWN
License: MIT
Platform: UNKNOWN
